flask_simpleview/__init__.py
Flask_SimpleView-1.0.0.dist-info/LICENSE
Flask_SimpleView-1.0.0.dist-info/METADATA
Flask_SimpleView-1.0.0.dist-info/WHEEL
Flask_SimpleView-1.0.0.dist-info/top_level.txt
Flask_SimpleView-1.0.0.dist-info/RECORD
