Metadata-Version: 2.1
Name: Flask-SimpleView
Version: 1.0.0
Summary: A very simple wrapper around flask's MethodView to ease the adding of views to the app or blueprints
Home-page: https://github.com/jackwardell/Flask-SimpleView/
Author: Jack Wardell
Author-email: jack@wardell.xyz
License: UNKNOWN
Keywords: flask
Platform: UNKNOWN
Classifier: Development Status :: 4 - Beta
Classifier: Programming Language :: Python
Classifier: Programming Language :: Python :: 3
Classifier: Programming Language :: Python :: 3.6
Classifier: Programming Language :: Python :: 3.7
Classifier: Programming Language :: Python :: 3.8
Classifier: License :: OSI Approved :: MIT License
Classifier: Operating System :: OS Independent
Classifier: Natural Language :: English
Classifier: Topic :: Internet :: WWW/HTTP :: Dynamic Content
Classifier: Topic :: Software Development :: Libraries :: Python Modules
Requires-Python: >=3.5
Requires-Dist: flask
